Workbook
Name expenseList: #REF!
Name IncomeList: #REF!

Sheet Welcome Tab
A1: WELCOME TO ONE MILLION ALLAWEE SAVINGS TRACKER (Your 12-Month Financial Friend) By Gift O. Udochukwu
A3: I welcome you
A4: Dear Financial Corper
A5: You got this tracker because you bought the book One Million Allawee, and you opened it because you just finished it. This already puts you ahead of most corps members who will serve alongside you this year.
A6: I want you to know first that this is not just a spreadsheet. It is a record of who you are becoming. Every naira you enter here is a vote for the version of yourself you decided to become the day you set your savings target.
A7: I built this tracker because knowing the system is not enough. You need a place to live in the system, to write the numbers down, watch them grow, and hold yourself accountable to the promise you made.
A8: Be consistent and use it honestly. Use it both in good and hard times. I wish you good luck as you do that.
A11: HOW TO USE THE SAVINGS TRACKER - 5 STEPS
A12: Step 1: Start with the Goal Tab.
A13: Before you enter any numbers, go to the Goal tab and fill in your name, your service year dates, your savings target, and your WHY. That is where your journey begins.
A14: Step 2: Come back on Allawee day every month.
A15: Open the Monthly Record tab. Enter your income, what you moved to savings, and your expenses for that month. It takes less than 10 minutes.
... A25: Yellow cells — milestone markers. These appear when you hit key targets.

Sheet Goal Tab
A1: WELCOME TO ONE MILLION ALLAWEE SAVINGS TRACKER (Your 12-Month Financial Friend) By Gift O. Udochukwu
A3: Corper Details
A5: CORPER NAME:
A7: SERVICES YEAR AND DATE:
A9: SAVINGS TARGET:
A11: WHY YOU WANT TO SAVE:

Sheet Income Tab
D1: ONE MILLION ALLAWEE SAVINGS TARGET
I2: Yearly Progress Chart
C3: SELECT YEAR | D3: 2026 | F3: SELECT MONTH | G3: JAN | P3: Target Amount | Q3: Actual Amount Saved
O4: JAN | P4: =D13 -> 0 | Q4: =E13 -> 0
C5: YEARLY SAVING TARGET | F5: MONTHLY SAVING TARGET | G5: =D5/12 -> 0 | O5: FEB | P5: =D14 -> 0 | Q5: =E14 -> 0
O6: MAR | P6: =D15 -> 0 | Q6: =E15 -> 0
C7: OTHER INFORMATION | O7: APR | P7: =D16 -> 0 | Q7: =E16 -> 0
O8: MAY | P8: =D17 -> 0 | Q8: =E17 -> 0
C9: TOTAL AMOUNT SAVED | D9: =SUM(E13:E24) -> 0 | F9: REMAINING TARGET SAVING | G9: =D5-D9 -> 0 | O9: JUN | P9: =D18 -> 0 | Q9: =E18 -> 0
O10: JUL | P10: =D19 -> 0 | Q10: =E19 -> 0
O11: AUG | P11: =D20 -> 0 | Q11: =E20 -> 0
B12: ALLAWEE DATE | C12: TOTAL MONTHLY INCOME | D12: MONTHLY SAVING TARGET | E12: ACTUAL AMOUNT SAVED | F12: DIFFERENCE | G12: BALANCE LEFT | O12: SEPT | P12: =D21 -> 0 | Q12: =E21 -> 0
B13: 46027 | D13: =$G$5 -> 0 | F13: ='Income Tab'!$E13-'Income Tab'!$D13 -> 0 | G13: =$D$5-SUM($E$13:E13) -> 0 | O13: OCT | P13: =D22 -> 0 | Q13: =E22 -> 0
B14: 46060 | D14: =$G$5 -> 0 | F14: ='Income Tab'!$E14-'Income Tab'!$D14 -> 0 | G14: =$D$5-SUM($E$13:E14) -> 0 | O14: NOV | P14: =D23 -> 0 | Q14: =E23 -> 0
B15: 46085 | D15: =$G$5 -> 0 | F15: ='Income Tab'!$E15-'Income Tab'!$D15 -> 0 | G15: =$D$5-SUM($E$13:E15) -> 0 | O15: DEC | P15: =D24 -> 0 | Q15: =E24 -> 0
B16: Apr 04, 2026 | D16: =$G$5 -> 0 | F16: ='Income Tab'!$E16-'Income Tab'!$D16 -> 0 | G16: =$D$5-SUM($E$13:E16) -> 0
B17: May 08, 2026 | D17: =$G$5 -> 0 | F17: ='Income Tab'!$E17-'Income Tab'!$D17 -> 0 | G17: =$D$5-SUM($E$13:E17) -> 0
B18: June 03, 2026 | D18: =$G$5 -> 0 | F18: ='Income Tab'!$E18-'Income Tab'!$D18 -> 0 | G18: =$D$5-SUM($E$13:E18) -> 0
D19: =$G$5 -> 0 | F19: ='Income Tab'!$E19-'Income Tab'!$D19 -> 0 | G19: =$D$5-SUM($E$13:E19) -> 0
D20: =$G$5 -> 0 | F20: ='Income Tab'!$E20-'Income Tab'!$D20 -> 0 | G20: =$D$5-SUM($E$13:E20) -> 0
D21: =$G$5 -> 0 | F21: ='Income Tab'!$E21-'Income Tab'!$D21 -> 0 | G21: =$D$5-SUM($E$13:E21) -> 0
D22: =$G$5 -> 0 | F22: ='Income Tab'!$E22-'Income Tab'!$D22 -> 0 | G22: =$D$5-SUM($E$13:E22) -> 0
D23: =$G$5 -> 0 | F23: ='Income Tab'!$E23-'Income Tab'!$D23 -> 0 | G23: =$D$5-SUM($E$13:E23) -> 0
D24: =$G$5 -> 0 | F24: ='Income Tab'!$E24-'Income Tab'!$D24 -> 0 | G24: =$D$5-SUM($E$13:E24) -> 0
